{
  "data": [{
    "title": "批放转化率排名",
    "series": [{
      "data": [100, 101, 102, 103, 104, 105],
      "type": "bar"
    }]
  }, {
    "title": "待签待放金额排名",
    "series": [{
      "name": "待签额",
      "data": [9600, 1540, 5420, 7841, 8469, 9547],
      "type": "bar"
    }, {
      "name": "待放额",
      "data": [2001, 1542, 4562, 4742, 2135, 3014],
      "type": "bar"
    }]
  }, {
    "title": "任务达成率排名",
    "series": [{
      "name": "放款任务",
      "data": [9600, 1540, 5420, 7841, 8469, 9999],
      "type": "bar"
    }, {
      "name": "放款额",
      "data": [2001, 1542, 4562, 4742, 2135, 3014],
      "type": "bar"
    }, {
      "name": "任务达成率",
      "data": [44, 42, 38, 33, 33, 31],
      "type": "line"
    }]
  }, {
    "title": "逾期排名",
    "series": [{
      "name": "M1($)",
      "data": [9600, 1540, 5420, 7841, 8469, 9999],
      "type": "bar"
    }, {
      "name": "C-M1(%)",
      "data": [2001, 1542, 4562, 4742, 2135, 3014],
      "type": "line"
    }, {
      "name": "警戒线",
      "data": [44, 42, 38, 33, 33, 31],
      "type": "lines"
    }]
  }]


}
